bokehgraph/__init__.py
bokehgraph/bokehgraph.py
bokehgraph/colormap.py
bokehgraph-1.1.0.dist-info/METADATA
bokehgraph-1.1.0.dist-info/WHEEL
bokehgraph-1.1.0.dist-info/licenses/LICENSE
bokehgraph-1.1.0.dist-info/RECORD
