Metadata-Version: 2.4
Name: bokehgraph
Version: 1.1.0
Summary: Interactive Graph visualization for networkX Graphs
Project-URL: Homepage, https://github.com/luerhard/bokehgraph
Author-email: Lukas Erhard <luerhard@googlemail.com>
License-Expression: MIT
License-File: LICENSE
Requires-Python: <4.0,>=3.9
Requires-Dist: bokeh<4.0,>=3.4.2
Requires-Dist: networkx>=3
Requires-Dist: numpy>=1.26; python_version >= '3.12'
Requires-Dist: numpy>=1.7; python_version <= '3.12'
